glycotrans/MSTokenizer.py
glycotrans/__init__.py
glycotrans/glycan_classes.pkl
glycotrans/utils.py
glycotrans/vocab_glycobart.json
glycotrans/vocab_glycobert.json
glycotrans-0.1.2.dist-info/licenses/LICENSE
glycotrans-0.1.2.dist-info/METADATA
glycotrans-0.1.2.dist-info/WHEEL
glycotrans-0.1.2.dist-info/top_level.txt
glycotrans-0.1.2.dist-info/RECORD
