Metadata-Version: 2.4
Name: glycotrans
Version: 0.1.2
Summary: A python package for glycan structure prediction from mass spectrometry data 
Author-email: Rudiyanto Gunawan <rgunawan@buffalo.edu>, Ejas Abtheen <ejasalth@buffalo.edu>
License: MIT
Project-URL: Homepage, https://github.com/CABSEL/glycotrans.git
Classifier: Development Status :: 4 - Beta
Classifier: Programming Language :: Python :: 3
Classifier: License :: OSI Approved :: MIT License
Classifier: Operating System :: OS Independent
Requires-Python: >=3.9
License-File: LICENSE
Requires-Dist: CandyCrunch==0.6.0
Requires-Dist: glycowork~=1.6.1
Requires-Dist: torch>2.1
Requires-Dist: transformers<5.0.0,>=4.50.0
Requires-Dist: pandas
Requires-Dist: numpy
Requires-Dist: pyopenms~=3.4
Dynamic: license-file
